khanaa/__init__.py
khanaa/ambiguity.py
khanaa/combination.py
khanaa/decomposition.py
khanaa/homophone.py
khanaa/main.py
khanaa/pronunciation.py
khanaa/setting.py
khanaa/speller.py
khanaa/thai_script.py
khanaa/thai_spelling.py
khanaa/utils.py
khanaa/word.py
khanaa-0.1.1.dist-info/LICENSE
khanaa-0.1.1.dist-info/METADATA
khanaa-0.1.1.dist-info/WHEEL
khanaa-0.1.1.dist-info/top_level.txt
khanaa-0.1.1.dist-info/RECORD
