Metadata-Version: 2.1
Name: khanaa
Version: 0.1.1
Summary: A Python tool for spelling Thai
Home-page: https://github.com/cakimpei/khanaa
Author: cakimpei
Author-email: cakimpei@gmail.com
Project-URL: Bug Tracker, https://github.com/cakimpei/khanaa/issues
Classifier: Programming Language :: Python :: 3
Classifier: License :: OSI Approved :: MIT License
Classifier: Operating System :: OS Independent
Requires-Python: >=3.7
License-File: LICENSE
